sdcd/__init__.py
sdcd/causal_model/__init__.py
sdcd/causal_model/mechanisms.py
sdcd/causal_model/model.py
sdcd/models/__init__.py
sdcd/models/_dagma.py
sdcd/models/_dcdfg.py
sdcd/models/_dcdi.py
sdcd/models/_gies.py
sdcd/models/_nobears.py
sdcd/models/_notears.py
sdcd/models/_sdcd.py
sdcd/models/_sortnregress.py
sdcd/models/base/_base_model.py
sdcd/models/modules.py
sdcd/simulated_data/__init__.py
sdcd/simulated_data/examples.py
sdcd/simulated_data/graph.py
sdcd/simulated_data/mechanisms.py
sdcd/simulated_data/utils.py
sdcd/third_party/callback.py
sdcd/third_party/dagma/__init__.py
sdcd/third_party/dagma/model.py
sdcd/third_party/dagma/module.py
sdcd/third_party/dcdfg/__init__.py
sdcd/third_party/dcdfg/model.py
sdcd/third_party/dcdfg/module.py
sdcd/third_party/dcdi/__init__.py
sdcd/third_party/dcdi/model.py
sdcd/third_party/dcdi/module.py
sdcd/third_party/nobears/__init__.py
sdcd/third_party/nobears/main.py
sdcd/third_party/notears/__init__.py
sdcd/third_party/notears/main.py
sdcd/third_party/sortnregress/__init__.py
sdcd/third_party/sortnregress/main.py
sdcd/third_party/utils/__init__.py
sdcd/third_party/utils/dag_optim.py
sdcd/third_party/utils/gumbel.py
sdcd/utils/__init__.py
sdcd/utils/train_utils.py
sdcd/utils/utils.py
sdcd-0.1.4.dist-info/LICENSE.md
sdcd-0.1.4.dist-info/METADATA
sdcd-0.1.4.dist-info/NOTICE.md
sdcd-0.1.4.dist-info/WHEEL
sdcd-0.1.4.dist-info/RECORD
