Metadata-Version: 2.1
Name: sdcd
Version: 0.1.4
Summary: Stable differentiable causal discovery for interventional data.
License: MIT
Author: Achille Nazaret
Author-email: aon2108@columbia.edu
Requires-Python: >=3.9
Classifier: Development Status :: 4 - Beta
Classifier: Intended Audience :: Science/Research
Classifier: License :: OSI Approved :: MIT License
Classifier: Natural Language :: English
Classifier: Programming Language :: Python :: 3
Classifier: Programming Language :: Python :: 3.9
Classifier: Programming Language :: Python :: 3.10
Classifier: Programming Language :: Python :: 3.11
Classifier: Programming Language :: Python :: 3.12
Provides-Extra: benchmark
Provides-Extra: tests
Requires-Dist: click (>=8.1.7,<9.0.0) ; extra == "benchmark"
Requires-Dist: networkx (>=3.2.1,<4.0.0)
Requires-Dist: numba (>=0.59.1,<0.60.0)
Requires-Dist: pandas (>=1.1.1,<2.0.0)
Requires-Dist: scipy (>=1.11.3,<2.0.0)
Requires-Dist: torch (>=2.1.0,<3.0.0)
Requires-Dist: tqdm (>=4.66.1,<5.0.0)
Requires-Dist: wandb (>=0.15.12,<0.16.0)
